finlearn/__init__.py
finlearn/analysis.py
finlearn/check.py
finlearn/plotter.py
finlearn/time_series.py
finlearn-0.0.463.dist-info/LICENSE
finlearn-0.0.463.dist-info/METADATA
finlearn-0.0.463.dist-info/WHEEL
finlearn-0.0.463.dist-info/top_level.txt
finlearn-0.0.463.dist-info/RECORD
