Metadata-Version: 2.1
Name: finlearn
Version: 0.0.463
Summary: A one-stop package for entire financial analysis and market prediction using Deep Learning
Author: Ankit Dutta
Author-email: ankitduttaiitkgp@gmail.com
License: Apache 2.0
Classifier: Programming Language :: Python :: 3
License-File: LICENSE
Requires-Dist: plotly
Requires-Dist: yfinance
Requires-Dist: matplotlib
Requires-Dist: pandas
Requires-Dist: seaborn
Requires-Dist: keras
Requires-Dist: datetime
